oh_my_theme/__init__.py
oh_my_theme/config.py
oh_my_theme/editor.py
oh_my_theme/main.py
oh_my_theme/preview.py
oh_my_theme/repositories.py
oh_my_theme/search.py
oh_my_theme-2.0.0.dist-info/licenses/LICENSE
oh_my_theme-2.0.0.dist-info/METADATA
oh_my_theme-2.0.0.dist-info/WHEEL
oh_my_theme-2.0.0.dist-info/entry_points.txt
oh_my_theme-2.0.0.dist-info/top_level.txt
oh_my_theme-2.0.0.dist-info/RECORD
