Metadata-Version: 2.4
Name: oh-my-theme
Version: 2.0.0
Summary: Terminal-based theme manager for Oh My Posh with preview, search, custom repositories, and theme customization
Author-email: AccidentallyStable <accidentallystable@proton.com>
Maintainer-email: Accidentallystable <accidentallystable@proton.com>
License-Expression: MIT
Project-URL: Homepage, https://github.com/mikeisfree/oh-my-theme
Project-URL: Repository, https://github.com/mikeisfree/oh-my-theme
Project-URL: Issues, https://github.com/mikeisfree/oh-my-theme/issues
Project-URL: Documentation, https://github.com/mikeisfree/oh-my-theme#readme
Keywords: oh-my-posh,terminal,theme,prompt,shell,bash,zsh,fish,customization,search,git,color-editor
Classifier: Development Status :: 5 - Production/Stable
Classifier: Environment :: Console :: Curses
Classifier: Intended Audience :: Developers
Classifier: Intended Audience :: End Users/Desktop
Classifier: Operating System :: POSIX :: Linux
Classifier: Operating System :: MacOS
Classifier: Programming Language :: Python :: 3
Classifier: Programming Language :: Python :: 3.6
Classifier: Programming Language :: Python :: 3.7
Classifier: Programming Language :: Python :: 3.8
Classifier: Programming Language :: Python :: 3.9
Classifier: Programming Language :: Python :: 3.10
Classifier: Programming Language :: Python :: 3.11
Classifier: Programming Language :: Python :: 3.12
Classifier: Topic :: System :: Shells
Classifier: Topic :: Terminals
Classifier: Topic :: Utilities
Requires-Python: >=3.6
License-File: LICENSE
Provides-Extra: dev
Requires-Dist: pytest>=6.0; extra == "dev"
Requires-Dist: pytest-cov; extra == "dev"
Requires-Dist: black; extra == "dev"
Requires-Dist: flake8; extra == "dev"
Requires-Dist: mypy; extra == "dev"
Dynamic: license-file
